MANIFEST.in
README.md
setup.py
silica/__init__.py
silica.egg-info/PKG-INFO
silica.egg-info/SOURCES.txt
silica.egg-info/dependency_links.txt
silica.egg-info/not-zip-safe
silica.egg-info/requires.txt
silica.egg-info/top_level.txt
silica/django_app/__init__.py
silica/django_app/apps.py
silica/django_app/models.py
silica/django_app/static/silica/fonts/glyphicons-halflings-regular.eot
silica/django_app/static/silica/fonts/glyphicons-halflings-regular.svg
silica/django_app/static/silica/fonts/glyphicons-halflings-regular.ttf
silica/django_app/static/silica/fonts/glyphicons-halflings-regular.woff
silica/django_app/static/silica/fonts/glyphicons-halflings-regular.woff2
silica/django_app/static/silica/lib/angular-1.4.6.min.js
silica/django_app/static/silica/lib/bootstrap-3.3.4.min.js
silica/django_app/static/silica/lib/bootstrap.min.css
silica/django_app/static/silica/lib/jquery-1.11.3.min.js
silica/django_app/static/silica/lib/jquery-ui-1.11.4.min.css
silica/django_app/static/silica/lib/jquery-ui-1.11.4.min.js
silica/django_app/static/silica/lib/jquery-ui-1.11.4.structure.min.css
silica/django_app/static/silica/lib/jquery-ui-1.11.4.theme.min.css
silica/django_app/static/silica/lib/ui-bootstrap-tpls-1.2.5.min.js
silica/django_app/static/silica/lib/images/ui-bg_diagonals-thick_18_b81900_40x40.png
silica/django_app/static/silica/lib/images/ui-bg_diagonals-thick_20_666666_40x40.png
silica/django_app/static/silica/lib/images/ui-bg_flat_10_000000_40x100.png
silica/django_app/static/silica/lib/images/ui-bg_glass_100_f6f6f6_1x400.png
silica/django_app/static/silica/lib/images/ui-bg_glass_100_fdf5ce_1x400.png
silica/django_app/static/silica/lib/images/ui-bg_glass_65_ffffff_1x400.png
silica/django_app/static/silica/lib/images/ui-bg_gloss-wave_35_f6a828_500x100.png
silica/django_app/static/silica/lib/images/ui-bg_highlight-soft_100_eeeeee_1x100.png
silica/django_app/static/silica/lib/images/ui-bg_highlight-soft_75_ffe45c_1x100.png
silica/django_app/static/silica/lib/images/ui-icons_222222_256x240.png
silica/django_app/static/silica/lib/images/ui-icons_228ef1_256x240.png
silica/django_app/static/silica/lib/images/ui-icons_ef8c08_256x240.png
