Metadata-Version: 1.1
Name: silica
Version: 0.0.3
Summary: An automation layer between frontend and backend code.  Currently supports Django and Angular.js
Home-page: https://zagaran.com
Author: Zagaran, Inc.
Author-email: zags@zagaran.com
License: MIT
Keywords: django angular interface
Platform: UNKNOWN
Classifier: Development Status :: 4 - Beta
Classifier: License :: OSI Approved :: MIT License
Classifier: Operating System :: MacOS :: MacOS X
Classifier: Operating System :: Microsoft :: Windows
Classifier: Operating System :: POSIX
Classifier: Programming Language :: Python
